{
  "accentColor": "{{appsmith.theme.colors.primaryColor}}",
  "animateLoading": true,
  "borderColor": "#E0DEDE",
  "borderRadius": "{{appsmith.theme.borderRadius.appBorderRadius}}",
  "borderWidth": "1",
  "bottomRow": 96,
  "boxShadow": "{{appsmith.theme.boxShadow.appBoxShadow}}",
  "cachedTableData": {},
  "canFreezeColumn": true,
  "childStylesheet": {
    "button": {
      "borderRadius": "{{appsmith.theme.borderRadius.appBorderRadius}}",
      "boxShadow": "none",
      "buttonColor": "{{appsmith.theme.colors.primaryColor}}"
    },
    "editActions": {
      "discardBorderRadius": "{{appsmith.theme.borderRadius.appBorderRadius}}",
      "discardButtonColor": "{{appsmith.theme.colors.primaryColor}}",
      "saveBorderRadius": "{{appsmith.theme.borderRadius.appBorderRadius}}",
      "saveButtonColor": "{{appsmith.theme.colors.primaryColor}}"
    },
    "iconButton": {
      "borderRadius": "{{appsmith.theme.borderRadius.appBorderRadius}}",
      "boxShadow": "none",
      "buttonColor": "{{appsmith.theme.colors.primaryColor}}"
    },
    "menuButton": {
      "borderRadius": "{{appsmith.theme.borderRadius.appBorderRadius}}",
      "boxShadow": "none",
      "menuColor": "{{appsmith.theme.colors.primaryColor}}"
    }
  },
  "columnOrder": [
    "_product_id",
    "Item_Name",
    "MRP",
    "Qty",
    "Price",
    "Gross__",
    "Sch",
    "Disc__",
    "Disc___",
    "Taxable__",
    "GST__",
    "GST__1",
    "Net__",
    "batch_id",
    "Invoiced_Qty",
    "_batches",
    "inventory_status",
    "return_to_stock"
  ],
  "columnUpdatedAt": 1775789035972,
  "columnWidthMap": {
    "Disc__": 90,
    "Disc___": 91,
    "GST__": 94,
    "GST__1": 103,
    "Gross__": 87,
    "Item_Name": 314,
    "MRP": 78,
    "Net__": 140,
    "Price": 82,
    "Qty": 68,
    "Sch": 82,
    "Taxable__": 111,
    "_product_id": 60
  },
  "customIsLoading": false,
  "customIsLoadingValue": "",
  "defaultPageSize": 0,
  "defaultSelectedRowIndex": 0,
  "defaultSelectedRowIndices": [
    0
  ],
  "delimiter": ",",
  "dynamicBindingPathList": [
    {
      "key": "accentColor"
    },
    {
      "key": "borderRadius"
    },
    {
      "key": "boxShadow"
    },
    {
      "key": "tableData"
    },
    {
      "key": "isVisible"
    },
    {
      "key": "primaryColumns._product_id.computedValue"
    },
    {
      "key": "primaryColumns.Item_Name.computedValue"
    },
    {
      "key": "primaryColumns.batch_id.computedValue"
    },
    {
      "key": "primaryColumns.Qty.computedValue"
    },
    {
      "key": "primaryColumns.Price.computedValue"
    },
    {
      "key": "primaryColumns.Sch.computedValue"
    },
    {
      "key": "primaryColumns.Disc__.computedValue"
    },
    {
      "key": "primaryColumns.GST__.computedValue"
    },
    {
      "key": "primaryColumns.Invoiced_Qty.computedValue"
    },
    {
      "key": "primaryColumns.Taxable__.computedValue"
    },
    {
      "key": "primaryColumns.GST__1.computedValue"
    },
    {
      "key": "primaryColumns.Net__.computedValue"
    },
    {
      "key": "primaryColumns.MRP.computedValue"
    },
    {
      "key": "primaryColumns.Gross__.computedValue"
    },
    {
      "key": "primaryColumns.Disc___.computedValue"
    },
    {
      "key": "primaryColumns._batches.computedValue"
    },
    {
      "key": "primaryColumns.batch_id.selectOptions"
    },
    {
      "key": "primaryColumns.inventory_status.computedValue"
    },
    {
      "key": "primaryColumns.return_to_stock.computedValue"
    }
  ],
  "dynamicPropertyPathList": [
    {
      "key": "tableData"
    },
    {
      "key": "isVisible"
    }
  ],
  "dynamicTriggerPathList": [
    {
      "key": "primaryColumns.Qty.onSubmit"
    },
    {
      "key": "primaryColumns.Sch.onSubmit"
    },
    {
      "key": "primaryColumns.Disc__.onSubmit"
    },
    {
      "key": "primaryColumns.batch_id.onOptionChange"
    },
    {
      "key": "primaryColumns.inventory_status.onOptionChange"
    }
  ],
  "enableClientSideSearch": true,
  "endOfData": false,
  "flexVerticalAlignment": "start",
  "horizontalAlignment": "LEFT",
  "inlineEditingSaveOption": "CUSTOM",
  "isLoading": false,
  "isSortable": true,
  "isVisible": "{{ radReturnType.selectedOptionValue === 'ITEMS' }}",
  "isVisibleDownload": true,
  "isVisibleFilters": false,
  "isVisiblePagination": true,
  "isVisibleSearch": true,
  "key": "cuzwgjnnfe",
  "label": "Data",
  "leftColumn": 0,
  "minWidth": 450,
  "mobileBottomRow": 58,
  "mobileLeftColumn": 0,
  "mobileRightColumn": 34,
  "mobileTopRow": 30,
  "needsErrorInfo": false,
  "originalBottomRow": 93,
  "originalTopRow": 40,
  "parentColumnSpace": 19.228125,
  "parentId": "9qgxcgjwpq",
  "parentRowSpace": 10,
  "primaryColumnId": "_product_id",
  "primaryColumns": {
    "Disc__": {
      "alias": "Disc %",
      "allowCellWrapping": false,
      "allowSameOptionsInNewRow": true,
      "cellBackground": "",
      "columnType": "number",
      "computedValue": "{{(() => { const tableData = tblCreditLines.processedTableData || []; return tableData.length > 0 ? tableData.map((currentRow, currentIndex) => (currentRow[\"Disc %\"])) : Disc % })()}}",
      "currencyCode": "USD",
      "decimals": 0,
      "enableFilter": true,
      "enableSort": true,
      "fontStyle": "",
      "horizontalAlignment": "LEFT",
      "id": "Disc__",
      "index": 6,
      "isCellEditable": true,
      "isCellVisible": true,
      "isDerived": false,
      "isDisabled": false,
      "isDiscardVisible": true,
      "isEditable": true,
      "isSaveVisible": true,
      "isVisible": true,
      "label": "Disc %",
      "notation": "standard",
      "onSubmit": "{{CN_Helper.updateRow();}}",
      "originalId": "Disc %",
      "sticky": "",
      "textColor": "",
      "textSize": "0.875rem",
      "thousandSeparator": true,
      "validation": {},
      "verticalAlignment": "CENTER",
      "width": 150
    },
    "Disc___": {
      "alias": "Disc. $",
      "allowCellWrapping": false,
      "allowSameOptionsInNewRow": true,
      "cellBackground": "",
      "columnType": "number",
      "computedValue": "{{(() => { const tableData = tblCreditLines.processedTableData || []; return tableData.length > 0 ? tableData.map((currentRow, currentIndex) => (currentRow[\"Disc. $\"])) : Disc. $ })()}}",
      "currencyCode": "USD",
      "decimals": 0,
      "enableFilter": true,
      "enableSort": true,
      "fontStyle": "",
      "horizontalAlignment": "LEFT",
      "id": "Disc___",
      "index": 11,
      "isCellEditable": false,
      "isCellVisible": true,
      "isDerived": false,
      "isDisabled": false,
      "isDiscardVisible": true,
      "isEditable": false,
      "isSaveVisible": true,
      "isVisible": true,
      "label": "Disc. $",
      "notation": "standard",
      "originalId": "Disc. $",
      "sticky": "",
      "textColor": "",
      "textSize": "0.875rem",
      "thousandSeparator": true,
      "validation": {},
      "verticalAlignment": "CENTER",
      "width": 150
    },
    "GST__": {
      "alias": "GST %",
      "allowCellWrapping": false,
      "allowSameOptionsInNewRow": true,
      "cellBackground": "",
      "columnType": "number",
      "computedValue": "{{(() => { const tableData = tblCreditLines.processedTableData || []; return tableData.length > 0 ? tableData.map((currentRow, currentIndex) => (currentRow[\"GST %\"])) : GST % })()}}",
      "currencyCode": "USD",
      "decimals": 0,
      "enableFilter": true,
      "enableSort": true,
      "fontStyle": "",
      "horizontalAlignment": "LEFT",
      "id": "GST__",
      "index": 7,
      "isCellEditable": false,
      "isCellVisible": true,
      "isDerived": false,
      "isDisabled": false,
      "isDiscardVisible": true,
      "isEditable": false,
      "isSaveVisible": true,
      "isVisible": true,
      "label": "GST %",
      "notation": "standard",
      "originalId": "GST %",
      "sticky": "",
      "textColor": "",
      "textSize": "0.875rem",
      "thousandSeparator": true,
      "validation": {},
      "verticalAlignment": "CENTER",
      "width": 150
    },
    "GST__1": {
      "alias": "GST $",
      "allowCellWrapping": false,
      "allowSameOptionsInNewRow": true,
      "cellBackground": "",
      "columnType": "number",
      "computedValue": "{{(() => { const tableData = tblCreditLines.processedTableData || []; return tableData.length > 0 ? tableData.map((currentRow, currentIndex) => (currentRow[\"GST $\"])) : GST $ })()}}",
      "currencyCode": "USD",
      "decimals": 0,
      "enableFilter": true,
      "enableSort": true,
      "fontStyle": "",
      "horizontalAlignment": "LEFT",
      "id": "GST__1",
      "index": 10,
      "isCellEditable": false,
      "isCellVisible": true,
      "isDerived": false,
      "isDisabled": false,
      "isDiscardVisible": true,
      "isEditable": false,
      "isSaveVisible": true,
      "isVisible": true,
      "label": "GST $",
      "notation": "standard",
      "originalId": "GST $",
      "sticky": "",
      "textColor": "",
      "textSize": "0.875rem",
      "thousandSeparator": true,
      "validation": {},
      "verticalAlignment": "CENTER",
      "width": 150
    },
    "Gross__": {
      "alias": "Gross $",
      "allowCellWrapping": false,
      "allowSameOptionsInNewRow": true,
      "cellBackground": "",
      "columnType": "number",
      "computedValue": "{{(() => { const tableData = tblCreditLines.processedTableData || []; return tableData.length > 0 ? tableData.map((currentRow, currentIndex) => (currentRow[\"Gross $\"])) : Gross $ })()}}",
      "currencyCode": "USD",
      "decimals": 0,
      "enableFilter": true,
      "enableSort": true,
      "fontStyle": "",
      "horizontalAlignment": "LEFT",
      "id": "Gross__",
      "index": 10,
      "isCellEditable": false,
      "isCellVisible": true,
      "isDerived": false,
      "isDisabled": false,
      "isDiscardVisible": true,
      "isEditable": false,
      "isSaveVisible": true,
      "isVisible": true,
      "label": "Gross $",
      "notation": "standard",
      "originalId": "Gross $",
      "sticky": "",
      "textColor": "",
      "textSize": "0.875rem",
      "thousandSeparator": true,
      "validation": {},
      "verticalAlignment": "CENTER",
      "width": 150
    },
    "Invoiced_Qty": {
      "alias": "Invoiced Qty",
      "allowCellWrapping": false,
      "allowSameOptionsInNewRow": true,
      "cellBackground": "",
      "columnType": "text",
      "computedValue": "{{(() => { const tableData = tblCreditLines.processedTableData || []; return tableData.length > 0 ? tableData.map((currentRow, currentIndex) => (currentRow[\"Invoiced Qty\"])) : Invoiced Qty })()}}",
      "currencyCode": "USD",
      "decimals": 0,
      "enableFilter": true,
      "enableSort": true,
      "fontStyle": "",
      "horizontalAlignment": "LEFT",
      "id": "Invoiced_Qty",
      "index": 8,
      "isCellEditable": false,
      "isCellVisible": true,
      "isDerived": false,
      "isDisabled": false,
      "isDiscardVisible": true,
      "isEditable": false,
      "isSaveVisible": true,
      "isVisible": false,
      "label": "Invoiced Qty",
      "notation": "standard",
      "originalId": "Invoiced Qty",
      "sticky": "",
      "textColor": "",
      "textSize": "0.875rem",
      "thousandSeparator": true,
      "validation": {},
      "verticalAlignment": "CENTER",
      "width": 150
    },
    "Item_Name": {
      "alias": "Item Name",
      "allowCellWrapping": false,
      "allowSameOptionsInNewRow": true,
      "cellBackground": "",
      "columnType": "text",
      "computedValue": "{{(() => { const tableData = tblCreditLines.processedTableData || []; return tableData.length > 0 ? tableData.map((currentRow, currentIndex) => (currentRow[\"Item Name\"])) : Item Name })()}}",
      "currencyCode": "USD",
      "decimals": 0,
      "enableFilter": true,
      "enableSort": true,
      "fontStyle": "",
      "horizontalAlignment": "LEFT",
      "id": "Item_Name",
      "index": 1,
      "isCellEditable": false,
      "isCellVisible": true,
      "isDerived": false,
      "isDisabled": false,
      "isDiscardVisible": true,
      "isEditable": false,
      "isSaveVisible": true,
      "isVisible": true,
      "label": "Item Name",
      "notation": "standard",
      "originalId": "Item Name",
      "sticky": "",
      "textColor": "",
      "textSize": "0.875rem",
      "thousandSeparator": true,
      "validation": {},
      "verticalAlignment": "CENTER",
      "width": 150
    },
    "MRP": {
      "alias": "MRP",
      "allowCellWrapping": false,
      "allowSameOptionsInNewRow": true,
      "cellBackground": "",
      "columnType": "number",
      "computedValue": "{{(() => { const tableData = tblCreditLines.processedTableData || []; return tableData.length > 0 ? tableData.map((currentRow, currentIndex) => (currentRow[\"MRP\"])) : MRP })()}}",
      "currencyCode": "USD",
      "decimals": 0,
      "enableFilter": true,
      "enableSort": true,
      "fontStyle": "",
      "horizontalAlignment": "LEFT",
      "id": "MRP",
      "index": 3,
      "isCellEditable": false,
      "isCellVisible": true,
      "isDerived": false,
      "isDisabled": false,
      "isDiscardVisible": true,
      "isEditable": false,
      "isSaveVisible": true,
      "isVisible": true,
      "label": "MRP",
      "notation": "standard",
      "originalId": "MRP",
      "sticky": "",
      "textColor": "",
      "textSize": "0.875rem",
      "thousandSeparator": true,
      "validation": {},
      "verticalAlignment": "CENTER",
      "width": 150
    },
    "Net__": {
      "alias": "Net $",
      "allowCellWrapping": false,
      "allowSameOptionsInNewRow": true,
      "cellBackground": "",
      "columnType": "number",
      "computedValue": "{{(() => { const tableData = tblCreditLines.processedTableData || []; return tableData.length > 0 ? tableData.map((currentRow, currentIndex) => (currentRow[\"Net $\"])) : Net $ })()}}",
      "currencyCode": "USD",
      "decimals": 0,
      "enableFilter": true,
      "enableSort": true,
      "fontStyle": "",
      "horizontalAlignment": "LEFT",
      "id": "Net__",
      "index": 11,
      "isCellEditable": false,
      "isCellVisible": true,
      "isDerived": false,
      "isDisabled": false,
      "isDiscardVisible": true,
      "isEditable": false,
      "isSaveVisible": true,
      "isVisible": true,
      "label": "Net $",
      "notation": "standard",
      "originalId": "Net $",
      "sticky": "",
      "textColor": "",
      "textSize": "0.875rem",
      "thousandSeparator": true,
      "validation": {},
      "verticalAlignment": "CENTER",
      "width": 150
    },
    "Price": {
      "alias": "Price",
      "allowCellWrapping": false,
      "allowSameOptionsInNewRow": true,
      "cellBackground": "",
      "columnType": "number",
      "computedValue": "{{(() => { const tableData = tblCreditLines.processedTableData || []; return tableData.length > 0 ? tableData.map((currentRow, currentIndex) => (currentRow[\"Price\"])) : Price })()}}",
      "currencyCode": "USD",
      "decimals": 0,
      "enableFilter": true,
      "enableSort": true,
      "fontStyle": "",
      "horizontalAlignment": "LEFT",
      "id": "Price",
      "index": 4,
      "isCellEditable": false,
      "isCellVisible": true,
      "isDerived": false,
      "isDisabled": false,
      "isDiscardVisible": true,
      "isEditable": false,
      "isSaveVisible": true,
      "isVisible": true,
      "label": "Price",
      "notation": "standard",
      "originalId": "Price",
      "sticky": "",
      "textColor": "",
      "textSize": "0.875rem",
      "thousandSeparator": true,
      "validation": {},
      "verticalAlignment": "CENTER",
      "width": 150
    },
    "Qty": {
      "alias": "Qty",
      "allowCellWrapping": false,
      "allowSameOptionsInNewRow": true,
      "cellBackground": "",
      "columnType": "number",
      "computedValue": "{{(() => { const tableData = tblCreditLines.processedTableData || []; return tableData.length > 0 ? tableData.map((currentRow, currentIndex) => (currentRow[\"Qty\"])) : Qty })()}}",
      "currencyCode": "USD",
      "decimals": 0,
      "enableFilter": true,
      "enableSort": true,
      "fontStyle": "",
      "horizontalAlignment": "LEFT",
      "id": "Qty",
      "index": 3,
      "isCellEditable": true,
      "isCellVisible": true,
      "isDerived": false,
      "isDisabled": false,
      "isDiscardVisible": true,
      "isEditable": true,
      "isSaveVisible": true,
      "isVisible": true,
      "label": "Qty",
      "notation": "standard",
      "onSubmit": "{{CN_Helper.updateRow();}}",
      "originalId": "Qty",
      "sticky": "",
      "textColor": "",
      "textSize": "0.875rem",
      "thousandSeparator": true,
      "validation": {},
      "verticalAlignment": "CENTER",
      "width": 150
    },
    "Sch": {
      "alias": "Sch",
      "allowCellWrapping": false,
      "allowSameOptionsInNewRow": true,
      "cellBackground": "",
      "columnType": "number",
      "computedValue": "{{(() => { const tableData = tblCreditLines.processedTableData || []; return tableData.length > 0 ? tableData.map((currentRow, currentIndex) => (currentRow[\"Sch\"])) : Sch })()}}",
      "currencyCode": "USD",
      "decimals": 0,
      "enableFilter": true,
      "enableSort": true,
      "fontStyle": "",
      "horizontalAlignment": "LEFT",
      "id": "Sch",
      "index": 5,
      "isCellEditable": true,
      "isCellVisible": true,
      "isDerived": false,
      "isDisabled": false,
      "isDiscardVisible": true,
      "isEditable": true,
      "isSaveVisible": true,
      "isVisible": true,
      "label": "Sch",
      "notation": "standard",
      "onSubmit": "{{CN_Helper.updateRow();}}",
      "originalId": "Sch",
      "sticky": "",
      "textColor": "",
      "textSize": "0.875rem",
      "thousandSeparator": true,
      "validation": {},
      "verticalAlignment": "CENTER",
      "width": 150
    },
    "Taxable__": {
      "alias": "Taxable $",
      "allowCellWrapping": false,
      "allowSameOptionsInNewRow": true,
      "cellBackground": "",
      "columnType": "number",
      "computedValue": "{{(() => { const tableData = tblCreditLines.processedTableData || []; return tableData.length > 0 ? tableData.map((currentRow, currentIndex) => (currentRow[\"Taxable $\"])) : Taxable $ })()}}",
      "currencyCode": "USD",
      "decimals": 0,
      "enableFilter": true,
      "enableSort": true,
      "fontStyle": "",
      "horizontalAlignment": "LEFT",
      "id": "Taxable__",
      "index": 9,
      "isCellEditable": false,
      "isCellVisible": true,
      "isDerived": false,
      "isDisabled": false,
      "isDiscardVisible": true,
      "isEditable": false,
      "isSaveVisible": true,
      "isVisible": true,
      "label": "Taxable $",
      "notation": "standard",
      "originalId": "Taxable $",
      "sticky": "",
      "textColor": "",
      "textSize": "0.875rem",
      "thousandSeparator": true,
      "validation": {},
      "verticalAlignment": "CENTER",
      "width": 150
    },
    "_batches": {
      "alias": "_batches",
      "allowCellWrapping": false,
      "allowSameOptionsInNewRow": true,
      "cellBackground": "",
      "columnType": "text",
      "computedValue": "{{(() => { const tableData = tblCreditLines.processedTableData || []; return tableData.length > 0 ? tableData.map((currentRow, currentIndex) => (currentRow[\"_batches\"])) : _batches })()}}",
      "currencyCode": "USD",
      "decimals": 0,
      "enableFilter": true,
      "enableSort": true,
      "fontStyle": "",
      "horizontalAlignment": "LEFT",
      "id": "_batches",
      "index": 16,
      "isCellEditable": false,
      "isCellVisible": true,
      "isDerived": false,
      "isDisabled": false,
      "isDiscardVisible": true,
      "isEditable": false,
      "isSaveVisible": true,
      "isVisible": false,
      "label": "_batches",
      "notation": "standard",
      "originalId": "_batches",
      "sticky": "",
      "textColor": "",
      "textSize": "0.875rem",
      "thousandSeparator": true,
      "validation": {},
      "verticalAlignment": "CENTER",
      "width": 150
    },
    "_product_id": {
      "alias": "_product_id",
      "allowCellWrapping": false,
      "allowSameOptionsInNewRow": true,
      "cellBackground": "",
      "columnType": "text",
      "computedValue": "{{(() => { const tableData = tblCreditLines.processedTableData || []; return tableData.length > 0 ? tableData.map((currentRow, currentIndex) => (currentRow[\"_product_id\"])) : _product_id })()}}",
      "currencyCode": "USD",
      "decimals": 0,
      "enableFilter": true,
      "enableSort": true,
      "fontStyle": "",
      "horizontalAlignment": "LEFT",
      "id": "_product_id",
      "index": 0,
      "isCellEditable": false,
      "isCellVisible": true,
      "isDerived": false,
      "isDisabled": false,
      "isDiscardVisible": true,
      "isEditable": false,
      "isSaveVisible": true,
      "isVisible": true,
      "label": "_product_id",
      "notation": "standard",
      "originalId": "_product_id",
      "sticky": "",
      "textColor": "",
      "textSize": "0.875rem",
      "thousandSeparator": true,
      "validation": {},
      "verticalAlignment": "CENTER",
      "width": 150
    },
    "batch_id": {
      "alias": "batch_id",
      "allowCellWrapping": false,
      "allowSameOptionsInNewRow": true,
      "cellBackground": "",
      "columnType": "select",
      "computedValue": "{{(() => { const tableData = tblCreditLines.processedTableData || []; return tableData.length > 0 ? tableData.map((currentRow, currentIndex) => (currentRow[\"batch_id\"])) : batch_id })()}}",
      "currencyCode": "USD",
      "decimals": 0,
      "enableFilter": true,
      "enableSort": true,
      "fontStyle": "",
      "horizontalAlignment": "LEFT",
      "id": "batch_id",
      "index": 2,
      "isCellEditable": true,
      "isCellVisible": true,
      "isDerived": false,
      "isDisabled": false,
      "isDiscardVisible": true,
      "isEditable": true,
      "isSaveVisible": true,
      "isVisible": true,
      "label": "batch_id",
      "notation": "standard",
      "onOptionChange": "{{CN_Helper.updateRow();}}",
      "originalId": "batch_id",
      "selectOptions": "{{(() => { const tableData = tblCreditLines.processedTableData || []; return tableData.length > 0 ? tableData.map((currentRow, currentIndex) => ( currentRow._batches.map(b => ({ label: b.batch_code, value: b.id })) )) :  currentRow._batches.map(b => ({ label: b.batch_code, value: b.id }))  })()}}",
      "sticky": "",
      "textColor": "",
      "textSize": "0.875rem",
      "thousandSeparator": true,
      "validation": {},
      "verticalAlignment": "CENTER",
      "width": 150
    },
    "inventory_status": {
      "alias": "inventory_status",
      "allowCellWrapping": false,
      "allowSameOptionsInNewRow": true,
      "cellBackground": "",
      "columnType": "select",
      "computedValue": "{{(() => { const tableData = tblCreditLines.processedTableData || []; return tableData.length > 0 ? tableData.map((currentRow, currentIndex) => (currentRow[\"inventory_status\"])) : inventory_status })()}}",
      "currencyCode": "USD",
      "decimals": 0,
      "enableFilter": true,
      "enableSort": true,
      "fontStyle": "",
      "horizontalAlignment": "LEFT",
      "id": "inventory_status",
      "index": 3,
      "isCellEditable": true,
      "isCellVisible": true,
      "isDerived": false,
      "isDisabled": false,
      "isDiscardVisible": true,
      "isEditable": true,
      "isSaveVisible": true,
      "isVisible": true,
      "label": "inventory_status",
      "notation": "standard",
      "onOptionChange": "{{CN_Helper.updateRow();}}",
      "originalId": "inventory_status",
      "selectOptions": "[\n  { \"label\": \"Good\", \"value\": \"Good\" },\n  { \"label\": \"Damage\", \"value\": \"Damage\" },\n  { \"label\": \"Expiry\", \"value\": \"Expiry\" }\n]\n",
      "sticky": "",
      "textColor": "",
      "textSize": "0.875rem",
      "thousandSeparator": true,
      "validation": {},
      "verticalAlignment": "CENTER",
      "width": 150
    },
    "return_to_stock": {
      "alias": "return_to_stock",
      "allowCellWrapping": false,
      "allowSameOptionsInNewRow": true,
      "cellBackground": "",
      "columnType": "checkbox",
      "computedValue": "{{(() => { const tableData = tblCreditLines.processedTableData || []; return tableData.length > 0 ? tableData.map((currentRow, currentIndex) => (currentRow[\"return_to_stock\"])) : return_to_stock })()}}",
      "currencyCode": "USD",
      "decimals": 0,
      "enableFilter": true,
      "enableSort": true,
      "fontStyle": "",
      "horizontalAlignment": "LEFT",
      "id": "return_to_stock",
      "index": 16,
      "isCellEditable": false,
      "isCellVisible": true,
      "isDerived": false,
      "isDisabled": false,
      "isDiscardVisible": true,
      "isEditable": false,
      "isSaveVisible": true,
      "isVisible": false,
      "label": "return_to_stock",
      "notation": "standard",
      "originalId": "return_to_stock",
      "sticky": "",
      "textColor": "",
      "textSize": "0.875rem",
      "thousandSeparator": true,
      "validation": {},
      "verticalAlignment": "CENTER",
      "width": 150
    }
  },
  "renderMode": "CANVAS",
  "responsiveBehavior": "fill",
  "rightColumn": 64,
  "searchKey": "",
  "showInlineEditingOptionDropdown": true,
  "tableData": "{{appsmith.store.GlobalCreditLinesData}}",
  "textSize": "0.875rem",
  "topRow": 43,
  "totalRecordsCount": 0,
  "type": "TABLE_WIDGET_V2",
  "version": 2,
  "verticalAlignment": "CENTER",
  "widgetId": "9vnf5lqvin",
  "widgetName": "tblCreditLines"
}