{
  "gitSyncId": "69a80abb79ac426a29eb8838_bb554712-ba19-443e-bc08-d58bf47d5bf6",
  "id": "Items_getAdjustementHistory",
  "pluginId": "restapi-plugin",
  "pluginType": "API",
  "unpublishedAction": {
    "actionConfiguration": {
      "autoGeneratedHeaders": [],
      "body": "",
      "bodyFormData": [],
      "encodeParamsToggle": true,
      "formData": {
        "apiContentType": "none"
      },
      "headers": [],
      "httpMethod": "GET",
      "httpVersion": "HTTP11",
      "paginationType": "NONE",
      "path": "/api/stock/adjust",
      "pluginSpecifiedTemplates": [
        {
          "value": true
        }
      ],
      "queryParameters": [
        {
          "key": "start_date",
          "value": "{{ StartDateWidget.selectedDate }}"
        },
        {
          "key": "end_date",
          "value": "{{ EndDateWidget.selectedDate }}"
        }
      ],
      "timeoutInMillisecond": 10000
    },
    "confirmBeforeExecute": false,
    "datasource": {
      "id": "RenderCloud",
      "isAutoGenerated": false,
      "name": "RenderCloud",
      "pluginId": "restapi-plugin"
    },
    "dynamicBindingPathList": [
      {
        "key": "queryParameters[0].value"
      },
      {
        "key": "queryParameters[1].value"
      }
    ],
    "name": "getAdjustementHistory",
    "pageId": "Items",
    "runBehaviour": "AUTOMATIC",
    "userSetOnLoad": false
  }
}