{
  "gitSyncId": "69a80abb79ac426a29eb8838_677e29de-c481-41b4-9c35-9f7de105e9ac",
  "id": "Settings_ThemeManager",
  "unpublishedCollection": {
    "name": "ThemeManager",
    "pageId": "Settings",
    "pluginId": "js-plugin",
    "pluginType": "JS",
    "variables": [
      {
        "name": "themes",
        "value": "{\n  light: {\n    primary: \"#4F46E5\",\n    background: \"#FFFFFF\",\n    surface: \"#F3F4F6\",\n    surfaceAlt: \"#E9EBF0\",\n    text: \"#111827\",\n    textMuted: \"#6B7280\",\n    border: \"#E5E7EB\",\n    borderAlt: \"#D1D5DB\",\n    danger: \"#EF4444\",\n    success: \"#10B981\",\n    warning: \"#F59E0B\",\n    radius: \"8px\",\n    radiusSm: \"6px\",\n    radiusLg: \"12px\",\n    shadow: \"0 1px 8px 0 rgba(0,0,0,0.08)\",\n    shadowSm: \"0 1px 3px 0 rgba(0,0,0,0.06)\",\n    shadowLg: \"0 4px 24px 0 rgba(0,0,0,0.12)\",\n    borderWidth: \"1\"\n  },\n  dark: {\n    primary: \"#818CF8\",\n    background: \"#111827\",\n    surface: \"#1F2937\",\n    surfaceAlt: \"#374151\",\n    text: \"#F9FAFB\",\n    textMuted: \"#9CA3AF\",\n    border: \"#374151\",\n    borderAlt: \"#4B5563\",\n    danger: \"#F87171\",\n    success: \"#34D399\",\n    warning: \"#FBBF24\",\n    radius: \"8px\",\n    radiusSm: \"6px\",\n    radiusLg: \"12px\",\n    shadow: \"0 4px 24px 0 rgba(0,0,0,0.4)\",\n    shadowSm: \"0 2px 8px 0 rgba(0,0,0,0.3)\",\n    shadowLg: \"0 8px 32px 0 rgba(0,0,0,0.5)\",\n    borderWidth: \"1\"\n  },\n  midnight: {\n    primary: \"#7C6AF7\",\n    background: \"#0A0A0F\",\n    surface: \"#0F0F1A\",\n    surfaceAlt: \"#15151F\",\n    text: \"#E2E2F0\",\n    textMuted: \"#6B6B8A\",\n    border: \"#1E1E2E\",\n    borderAlt: \"#2A2A3E\",\n    danger: \"#F87171\",\n    success: \"#34D399\",\n    warning: \"#FBBF24\",\n    radius: \"8px\",\n    radiusSm: \"6px\",\n    radiusLg: \"12px\",\n    shadow: \"0 4px 24px 0 rgba(0,0,0,0.6)\",\n    shadowSm: \"0 2px 8px 0 rgba(0,0,0,0.4)\",\n    shadowLg: \"0 8px 32px 0 rgba(0,0,0,0.7)\",\n    borderWidth: \"1\"\n  },\n  frost: {\n    primary: \"#0EA5E9\",\n    background: \"#F8FAFC\",\n    surface: \"#FFFFFF\",\n    surfaceAlt: \"#F1F5F9\",\n    text: \"#0F172A\",\n    textMuted: \"#64748B\",\n    border: \"#E2E8F0\",\n    borderAlt: \"#CBD5E1\",\n    danger: \"#F43F5E\",\n    success: \"#10B981\",\n    warning: \"#F59E0B\",\n    radius: \"12px\",\n    radiusSm: \"8px\",\n    radiusLg: \"20px\",\n    shadow: \"0 4px 6px -1px rgba(0, 0, 0, 0.05), 0 2px 4px -2px rgba(0, 0, 0, 0.05)\",\n    shadowSm: \"0 1px 2px 0 rgba(0, 0, 0, 0.05)\",\n    shadowLg: \"0 20px 25px -5px rgba(0, 0, 0, 0.1), 0 8px 10px -6px rgba(0, 0, 0, 0.1)\",\n    borderWidth: \"1\"\n  },\n  orchid: {\n    primary: \"#8B5CF6\",\n    background: \"#FAF5FF\",\n    surface: \"#FFFFFF\",\n    surfaceAlt: \"#F3E8FF\",\n    text: \"#2E1065\",\n    textMuted: \"#7E22CE\",\n    border: \"#E9D5FF\",\n    borderAlt: \"#D8B4FE\",\n    danger: \"#E11D48\",\n    success: \"#059669\",\n    warning: \"#D97706\",\n    radius: \"16px\",\n    radiusSm: \"8px\",\n    radiusLg: \"24px\",\n    shadow: \"0 10px 15px -3px rgba(139, 92, 246, 0.1)\",\n    shadowSm: \"0 4px 6px -1px rgba(139, 92, 246, 0.05)\",\n    shadowLg: \"0 25px 50px -12px rgba(139, 92, 246, 0.25)\",\n    borderWidth: \"1\"\n  },\n  sage: {\n    primary: \"#059669\",\n    background: \"#F9FAF7\",\n    surface: \"#FFFFFF\",\n    surfaceAlt: \"#F0F2EE\",\n    text: \"#1A2E1A\",\n    textMuted: \"#526352\",\n    border: \"#E1E5DE\",\n    borderAlt: \"#C9D1C5\",\n    danger: \"#DC2626\",\n    success: \"#16A34A\",\n    warning: \"#CA8A04\",\n    radius: \"4px\",\n    radiusSm: \"2px\",\n    radiusLg: \"8px\",\n    shadow: \"0 1px 2px 0 rgba(0, 0, 0, 0.05)\",\n    shadowSm: \"0 1px 1px 0 rgba(0, 0, 0, 0.05)\",\n    shadowLg: \"0 10px 15px -3px rgba(0, 0, 0, 0.1)\",\n    borderWidth: \"1.5\"\n  },\n  nebula: {\n    primary: \"#A78BFA\",\n    background: \"#0F172A\",\n    surface: \"#1E293B\",\n    surfaceAlt: \"#334155\",\n    text: \"#F1F5F9\",\n    textMuted: \"#94A3B8\",\n    border: \"#334155\",\n    borderAlt: \"#475569\",\n    danger: \"#FB7185\",\n    success: \"#34D399\",\n    warning: \"#FBBF24\",\n    radius: \"12px\",\n    radiusSm: \"8px\",\n    radiusLg: \"20px\",\n    shadow: \"0 4px 20px 0 rgba(167, 139, 250, 0.15)\",\n    shadowSm: \"0 2px 8px 0 rgba(0, 0, 0, 0.4)\",\n    shadowLg: \"0 12px 40px 0 rgba(167, 139, 250, 0.25)\",\n    borderWidth: \"1\"\n  },\n  obsidian: {\n    primary: \"#FFFFFF\",\n    background: \"#000000\",\n    surface: \"#111111\",\n    surfaceAlt: \"#1C1C1C\",\n    text: \"#EDEDED\",\n    textMuted: \"#888888\",\n    border: \"#262626\",\n    borderAlt: \"#3F3F3F\",\n    danger: \"#FF453A\",\n    success: \"#32D74B\",\n    warning: \"#FFD60A\",\n    radius: \"8px\",\n    radiusSm: \"4px\",\n    radiusLg: \"16px\",\n    shadow: \"0 0 0 1px rgba(255,255,255,0.05)\",\n    shadowSm: \"0 2px 4px rgba(0,0,0,0.5)\",\n    shadowLg: \"0 20px 40px rgba(0,0,0,0.6)\",\n    borderWidth: \"1\"\n  },\n  evergreen: {\n    primary: \"#00DC82\",\n    background: \"#060D0A\",\n    surface: \"#0D1A14\",\n    surfaceAlt: \"#172B21\",\n    text: \"#ECF3F0\",\n    textMuted: \"#82968E\",\n    border: \"#1C3328\",\n    borderAlt: \"#2D4D3D\",\n    danger: \"#F87171\",\n    success: \"#34D399\",\n    warning: \"#FBBF24\",\n    radius: \"10px\",\n    radiusSm: \"6px\",\n    radiusLg: \"18px\",\n    shadow: \"0 10px 15px -3px rgba(0, 0, 0, 0.4)\",\n    shadowSm: \"0 4px 6px -1px rgba(0, 0, 0, 0.3)\",\n    shadowLg: \"0 25px 50px -12px rgba(0, 0, 0, 0.6)\",\n    borderWidth: \"1\"\n  },\n  brand: {\n    primary: \"#E11D48\",\n    background: \"#FFF1F2\",\n    surface: \"#FFE4E6\",\n    surfaceAlt: \"#FECDD3\",\n    text: \"#1F2937\",\n    textMuted: \"#6B7280\",\n    border: \"#FECDD3\",\n    borderAlt: \"#FDA4AF\",\n    danger: \"#BE123C\",\n    success: \"#059669\",\n    warning: \"#D97706\",\n    radius: \"8px\",\n    radiusSm: \"6px\",\n    radiusLg: \"12px\",\n    shadow: \"0 1px 8px 0 rgba(225,29,72,0.08)\",\n    shadowSm: \"0 1px 3px 0 rgba(225,29,72,0.06)\",\n    shadowLg: \"0 4px 24px 0 rgba(225,29,72,0.15)\",\n    borderWidth: \"1\"\n  },\n  nothingWhite: {\n    primary: \"#EB001B\",\n    background: \"#FFFFFF\",\n    surface: \"#F2F2F2\",\n    surfaceAlt: \"#E5E5E5\",\n    text: \"#000000\",\n    textMuted: \"#707070\",\n    border: \"#000000\",\n    borderAlt: \"#D1D1D1\",\n    danger: \"#EB001B\",\n    success: \"#00FF41\",\n    warning: \"#FFBF00\",\n    radius: \"0px\",\n    radiusSm: \"0px\",\n    radiusLg: \"24px\",\n    shadow: \"4px 4px 0px 0px rgba(0,0,0,1)\",\n    shadowSm: \"2px 2px 0px 0px rgba(0,0,0,1)\",\n    shadowLg: \"8px 8px 0px 0px rgba(0,0,0,1)\",\n    borderWidth: \"1.5\"\n  },\n  nothingBlack: {\n    primary: \"#EB001B\",\n    background: \"#000000\",\n    surface: \"#121212\",\n    surfaceAlt: \"#1F1F1F\",\n    text: \"#FFFFFF\",\n    textMuted: \"#A0A0A0\",\n    border: \"#262626\",\n    borderAlt: \"#404040\",\n    danger: \"#EB001B\",\n    success: \"#00FF41\",\n    warning: \"#FFBF00\",\n    radius: \"16px\",\n    radiusSm: \"8px\",\n    radiusLg: \"32px\",\n    shadow: \"0 0 10px 0 rgba(255,255,255,0.1)\",\n    shadowSm: \"0 0 5px 0 rgba(255,255,255,0.05)\",\n    shadowLg: \"0 0 25px 0 rgba(255,255,255,0.15)\",\n    borderWidth: \"1\"\n  },\n  paper: {\n    primary: \"#111111\",\n    background: \"#FDFDFD\",\n    surface: \"#FFFFFF\",\n    surfaceAlt: \"#F5F5F5\",\n    text: \"#000000\",\n    textMuted: \"#737373\",\n    border: \"#E5E5E5\",\n    borderAlt: \"#111111\",\n    danger: \"#FF3B30\",\n    success: \"#000000\",\n    warning: \"#FFCC00\",\n    radius: \"0px\",\n    radiusSm: \"0px\",\n    radiusLg: \"0px\",\n    shadow: \"0 0 0 1px rgba(0,0,0,0.05)\",\n    shadowSm: \"0 1px 2px rgba(0,0,0,0.1)\",\n    shadowLg: \"0 12px 24px rgba(0,0,0,0.05)\",\n    borderWidth: \"1\"\n  },\n  alabaster: {\n    primary: \"#434343\",\n    background: \"#F7F7F2\",\n    surface: \"#FFFFFF\",\n    surfaceAlt: \"#EFEEE5\",\n    text: \"#1C1C1A\",\n    textMuted: \"#8C8C85\",\n    border: \"#E2E2D9\",\n    borderAlt: \"#C6C6B5\",\n    danger: \"#B91C1C\",\n    success: \"#166534\",\n    warning: \"#92400E\",\n    radius: \"20px\",\n    radiusSm: \"10px\",\n    radiusLg: \"32px\",\n    shadow: \"0 10px 30px -10px rgba(0,0,0,0.05)\",\n    shadowSm: \"0 2px 10px rgba(0,0,0,0.02)\",\n    shadowLg: \"0 30px 60px -12px rgba(0,0,0,0.08)\",\n    borderWidth: \"1\"\n  },\n  ghost: {\n    primary: \"#6366F1\",\n    background: \"#F1F5F9\",\n    surface: \"#FFFFFFCC\",\n    surfaceAlt: \"#E2E8F0\",\n    text: \"#0F172A\",\n    textMuted: \"#64748B\",\n    border: \"#FFFFFF\",\n    borderAlt: \"#CBD5E1\",\n    danger: \"#EF4444\",\n    success: \"#22C55E\",\n    warning: \"#F59E0B\",\n    radius: \"12px\",\n    radiusSm: \"6px\",\n    radiusLg: \"24px\",\n    shadow: \"0 8px 32px 0 rgba(31, 38, 135, 0.07)\",\n    shadowSm: \"0 4px 8px 0 rgba(0, 0, 0, 0.04)\",\n    shadowLg: \"0 12px 48px 0 rgba(0, 0, 0, 0.1)\",\n    borderWidth: \"2\"\n  }\n}"
      },
      {
        "name": "defaultTheme",
        "value": "\"ghost\""
      }
    ]
  }
}