{
  "gitSyncId": "69a80abb79ac426a29eb8838_7fc47557-6146-4b8c-8ba7-3e2b9c07d86e",
  "id": "Transactions_DeleteTransferApi",
  "pluginId": "restapi-plugin",
  "pluginType": "API",
  "unpublishedAction": {
    "actionConfiguration": {
      "autoGeneratedHeaders": [
        {
          "key": "content-type",
          "value": "application/json"
        }
      ],
      "body": "",
      "bodyFormData": [],
      "encodeParamsToggle": true,
      "formData": {
        "apiContentType": "application/json"
      },
      "headers": [],
      "httpMethod": "DELETE",
      "httpVersion": "HTTP11",
      "paginationType": "NONE",
      "path": "/api/finance/transfers/{{tblInternalTransfer.triggeredRow.id}}",
      "pluginSpecifiedTemplates": [
        {
          "value": true
        }
      ],
      "queryParameters": [],
      "timeoutInMillisecond": 10000
    },
    "confirmBeforeExecute": false,
    "datasource": {
      "id": "RenderCloud",
      "isAutoGenerated": false,
      "name": "RenderCloud",
      "pluginId": "restapi-plugin"
    },
    "dynamicBindingPathList": [
      {
        "key": "path"
      }
    ],
    "name": "DeleteTransferApi",
    "pageId": "Transactions",
    "runBehaviour": "MANUAL",
    "userSetOnLoad": false
  }
}