{
  "gitSyncId": "69a80abb79ac426a29eb8838_ddab97be-eff7-4cf6-b8fa-645e978035f5",
  "id": "Debit Notes_getDocNo",
  "pluginId": "restapi-plugin",
  "pluginType": "API",
  "unpublishedAction": {
    "actionConfiguration": {
      "autoGeneratedHeaders": [],
      "body": "",
      "bodyFormData": [],
      "encodeParamsToggle": true,
      "formData": {
        "apiContentType": "none"
      },
      "headers": [],
      "httpMethod": "GET",
      "httpVersion": "HTTP11",
      "paginationType": "NONE",
      "path": "/api/documents/all-sequences",
      "pluginSpecifiedTemplates": [
        {
          "value": true
        }
      ],
      "queryParameters": [],
      "timeoutInMillisecond": 10000
    },
    "confirmBeforeExecute": false,
    "datasource": {
      "id": "RenderCloud",
      "isAutoGenerated": false,
      "name": "RenderCloud",
      "pluginId": "restapi-plugin"
    },
    "dynamicBindingPathList": [],
    "name": "getDocNo",
    "pageId": "Debit Notes",
    "runBehaviour": "AUTOMATIC",
    "userSetOnLoad": false
  }
}