{
  "gitSyncId": "69a80abb79ac426a29eb8838_5e3f8118-3253-4873-bca9-638835ace6ad",
  "id": "Schemes_PriceSlab_Utils.addPriceSlab",
  "pluginId": "js-plugin",
  "pluginType": "JS",
  "unpublishedAction": {
    "actionConfiguration": {
      "encodeParamsToggle": true,
      "jsArguments": [],
      "paginationType": "NONE",
      "timeoutInMillisecond": 10000
    },
    "collectionId": "Schemes_PriceSlab_Utils",
    "confirmBeforeExecute": false,
    "datasource": {
      "isAutoGenerated": false,
      "name": "UNUSED_DATASOURCE",
      "pluginId": "js-plugin"
    },
    "dynamicBindingPathList": [
      {
        "key": "body"
      }
    ],
    "fullyQualifiedName": "PriceSlab_Utils.addPriceSlab",
    "name": "addPriceSlab",
    "pageId": "Schemes",
    "runBehaviour": "MANUAL",
    "userSetOnLoad": false
  }
}