{
  "accentColor": "{{appsmith.theme.colors.primaryColor}}",
  "allowSelectAll": true,
  "animateLoading": true,
  "borderRadius": "{{appsmith.theme.borderRadius.appBorderRadius}}",
  "bottomRow": 7,
  "boxShadow": "none",
  "defaultOptionValue": "",
  "dynamicBindingPathList": [
    {
      "key": "accentColor"
    },
    {
      "key": "borderRadius"
    },
    {
      "key": "sourceData"
    }
  ],
  "dynamicHeight": "AUTO_HEIGHT",
  "dynamicPropertyPathList": [
    {
      "key": "sourceData"
    }
  ],
  "dynamicTriggerPathList": [],
  "isDisabled": false,
  "isFilterable": true,
  "isLoading": false,
  "isRequired": false,
  "isVisible": true,
  "key": "f1i0sn6pct",
  "labelAlignment": "left",
  "labelPosition": "Top",
  "labelText": "Select Customers",
  "labelTextSize": "0.875rem",
  "labelWidth": 5,
  "leftColumn": 0,
  "maxDynamicHeight": 9000,
  "minDynamicHeight": 4,
  "minWidth": 450,
  "mobileBottomRow": 7,
  "mobileLeftColumn": 0,
  "mobileRightColumn": 20,
  "mobileTopRow": 0,
  "needsErrorInfo": false,
  "optionLabel": "label",
  "optionValue": "value",
  "originalBottomRow": 7,
  "originalTopRow": 0,
  "parentColumnSpace": 13.00244140625,
  "parentId": "im1ubl1tue",
  "parentRowSpace": 10,
  "placeholderText": "Select option(s)",
  "renderMode": "CANVAS",
  "responsiveBehavior": "fill",
  "rightColumn": 16,
  "serverSideFiltering": false,
  "shouldScrollContents": true,
  "sourceData": "{{getCustomers.data.map( (obj) =>{ return  {'label': obj.customer_name, 'value': obj.id } })}}",
  "topRow": 0,
  "type": "MULTI_SELECT_WIDGET_V2",
  "version": 1,
  "widgetId": "8u66bdqiic",
  "widgetName": "ms_targetCustomers"
}