{
  "gitSyncId": "69a80abb79ac426a29eb8838_50846653-9f34-4b0f-b4e9-a8ca5b3b0302",
  "id": "Customer_getRoutes",
  "pluginId": "restapi-plugin",
  "pluginType": "API",
  "unpublishedAction": {
    "actionConfiguration": {
      "autoGeneratedHeaders": [],
      "body": "",
      "bodyFormData": [],
      "encodeParamsToggle": true,
      "formData": {
        "apiContentType": "none"
      },
      "headers": [],
      "httpMethod": "GET",
      "httpVersion": "HTTP11",
      "paginationType": "NONE",
      "path": "/api/master/routes",
      "pluginSpecifiedTemplates": [
        {
          "value": true
        }
      ],
      "queryParameters": [],
      "timeoutInMillisecond": 10000
    },
    "confirmBeforeExecute": false,
    "datasource": {
      "id": "RenderCloud",
      "isAutoGenerated": false,
      "name": "RenderCloud",
      "pluginId": "restapi-plugin"
    },
    "dynamicBindingPathList": [],
    "name": "getRoutes",
    "pageId": "Customer",
    "runBehaviour": "AUTOMATIC",
    "userSetOnLoad": false
  }
}